pcg_c_0_0_1_0_94.so
pypcg.py
pcg_basic/pcg_basic.c
pcg_basic/pcg_basic.h
pypcg-0.0.3.dist-info/DESCRIPTION.rst
pypcg-0.0.3.dist-info/METADATA
pypcg-0.0.3.dist-info/metadata.json
pypcg-0.0.3.dist-info/RECORD
pypcg-0.0.3.dist-info/top_level.txt
pypcg-0.0.3.dist-info/WHEEL
