Metadata-Version: 2.0
Name: pypcg
Version: 0.0.3
Summary: UNKNOWN
Home-page: https://github.com/robojeb/pypcg
Author: Jeb Brooks
Author-email: jbrooks+pypcg@hmc.edu
License: MIT
Platform: UNKNOWN
Requires-Dist: cffi
